QNeura/__config__.py
QNeura/__init__.py
QNeura/lib.py
QNeura/nqs.py
QNeura/references.py
qneura-0.0.1.dist-info/WHEEL
qneura-0.0.1.dist-info/METADATA
qneura-0.0.1.dist-info/RECORD
