Metadata-Version: 2.4
Name: QNeura
Version: 0.0.1
Summary: Open Source Pakcage for Solving Quantum Many-body problems via Neural network quantum states
Author-email: Yu Zhang <zhy@lanl.gov>
Requires-Python: >=3.8
Classifier: Programming Language :: Python :: 3
Classifier: Operating System :: OS Independent
